odoo/addons/odoo_odoo_test/__init__.py
odoo/addons/odoo_odoo_test/__manifest__.py
odoo_odoo_test-0.0.2.dist-info/METADATA
odoo_odoo_test-0.0.2.dist-info/WHEEL
odoo_odoo_test-0.0.2.dist-info/top_level.txt
odoo_odoo_test-0.0.2.dist-info/RECORD
