Metadata-Version: 2.1
Name: odoo-odoo-test
Version: 0.0.2
Summary: Odoo customizations for odoo-test
Home-page: UNKNOWN
Author: Coopdevs
Author-email: UNKNOWN
License: GPL
Platform: UNKNOWN
